mms_ok/__init__.py
mms_ok/bist.py
mms_ok/bist_util.py
mms_ok/fpga.py
mms_ok/fpga_components.py
mms_ok/fpga_config.py
mms_ok/fpga_old.py
mms_ok/ok_setup.py
mms_ok/pipeoutdata.py
mms_ok/validation.py
tests/__init__.py
tests/test_conversion.py
tests/test_text_reordering.py
mms_ok-1.1.2.dist-info/LICENSE
mms_ok-1.1.2.dist-info/METADATA
mms_ok-1.1.2.dist-info/WHEEL
mms_ok-1.1.2.dist-info/top_level.txt
mms_ok-1.1.2.dist-info/RECORD
