Metadata-Version: 2.1
Name: mms_ok
Version: 1.1.2
Summary: Python package for interfacing with Opal Kelly FPGA boards
Author-email: Juyoung Oh <juyoung.oh@snu.ac.kr>
License: MIT License
Project-URL: Repository, https://github.com/ojy0216/mms_ok
Classifier: Intended Audience :: Science/Research
Classifier: Programming Language :: Python :: 3
Classifier: Topic :: Scientific/Engineering
Requires-Python: >=3.7
License-File: LICENSE
Requires-Dist: numpy
Requires-Dist: bitslice
Requires-Dist: loguru
Requires-Dist: rich
Requires-Dist: tqdm
